evoboost/__init__.py
evoboost/core.py
evoboost-0.1.0.dist-info/licenses/LICENSE
evoboost-0.1.0.dist-info/METADATA
evoboost-0.1.0.dist-info/WHEEL
evoboost-0.1.0.dist-info/top_level.txt
evoboost-0.1.0.dist-info/RECORD
